MANIFEST.in
README.md
setup.py
bin/pypi_versions
pypi_versions/__init__.py
pypi_versions/_version.py
pypi_versions/pypi_versions.py
pypi_versions.egg-info/PKG-INFO
pypi_versions.egg-info/SOURCES.txt
pypi_versions.egg-info/dependency_links.txt
pypi_versions.egg-info/requires.txt
pypi_versions.egg-info/top_level.txt