Metadata-Version: 2.1
Name: pypi-versions
Version: 0.1.1
Summary: Compare local depdenencies against Pypi.
Home-page: https://github.com/normoes/pypi_versions
Author: Norman Moeschter-Schenck
Author-email: norman.moeschter@gmail.com
License: UNKNOWN
Download-URL: https://github.com/normoes/pypi_versions/archive/v0.1.1.tar.gz
Platform: UNKNOWN
Classifier: Development Status :: 5 - Production/Stable
Classifier: Intended Audience :: Developers
Classifier: License :: OSI Approved :: MIT License
Classifier: Natural Language :: English
Classifier: Programming Language :: Python
